[
  {
    "gameId": "20260517WONC02026",
    "gameDate": "20260517",
    "opponent": "키움",
    "inning": 9,
    "homeOrAway": "1",
    "batOrder": 8,
    "batterName": "안중열",
    "batterPcode": "64022",
    "pitcherName": "유토",
    "pitcherPcode": "56348",
    "resultCode": "O",
    "resultText": "안중열 : 2루수 플라이 아웃",
    "base1": 0,
    "base2": 0,
    "base3": 0,
    "outCount": 0,
    "pitchCount": 3,
    "lastPitchSpeed": "152",
    "lastPitchType": "직구"
  },
  {
    "gameId": "20260515WONC02026",
    "gameDate": "20260515",
    "opponent": "키움",
    "inning": 6,
    "homeOrAway": "1",
    "batOrder": 8,
    "batterName": "안중열",
    "batterPcode": "64022",
    "pitcherName": "알칸타라",
    "pitcherPcode": "69045",
    "resultCode": "K",
    "resultText": "안중열 : 삼진 아웃",
    "base1": 1,
    "base2": 0,
    "base3": 0,
    "outCount": 0,
    "pitchCount": 3,
    "lastPitchSpeed": "136",
    "lastPitchType": "포크"
  },
  {
    "gameId": "20260515WONC02026",
    "gameDate": "20260515",
    "opponent": "키움",
    "inning": 3,
    "homeOrAway": "1",
    "batOrder": 8,
    "batterName": "안중열",
    "batterPcode": "64022",
    "pitcherName": "알칸타라",
    "pitcherPcode": "69045",
    "resultCode": "O",
    "resultText": "안중열 : 중견수 플라이 아웃",
    "base1": 0,
    "base2": 0,
    "base3": 0,
    "outCount": 1,
    "pitchCount": 2,
    "lastPitchSpeed": "151",
    "lastPitchType": "직구"
  }
]