[
  {
    "gameId": "20260526KTOB02026",
    "gameDate": "20260526",
    "opponent": "KT",
    "inning": 8,
    "homeOrAway": "1",
    "batOrder": 9,
    "batterName": "이유찬",
    "batterPcode": "67207",
    "pitcherName": "한승혁",
    "pitcherPcode": "61666",
    "resultCode": "O",
    "resultText": "이유찬 : 좌익수 플라이 아웃",
    "base1": 1,
    "base2": 0,
    "base3": 0,
    "outCount": 2,
    "pitchCount": 5,
    "lastPitchSpeed": "135",
    "lastPitchType": "슬라이더"
  },
  {
    "gameId": "20260526KTOB02026",
    "gameDate": "20260526",
    "opponent": "KT",
    "inning": 6,
    "homeOrAway": "1",
    "batOrder": 9,
    "batterName": "이유찬",
    "batterPcode": "67207",
    "pitcherName": "보쉴리",
    "pitcherPcode": "56036",
    "resultCode": "O",
    "resultText": "이유찬 : 우익수 플라이 아웃",
    "base1": 0,
    "base2": 1,
    "base3": 0,
    "outCount": 1,
    "pitchCount": 1,
    "lastPitchSpeed": "133",
    "lastPitchType": "스위퍼"
  },
  {
    "gameId": "20260526KTOB02026",
    "gameDate": "20260526",
    "opponent": "KT",
    "inning": 3,
    "homeOrAway": "1",
    "batOrder": 9,
    "batterName": "이유찬",
    "batterPcode": "67207",
    "pitcherName": "보쉴리",
    "pitcherPcode": "56036",
    "resultCode": "O",
    "resultText": "이유찬 : 우익수 플라이 아웃",
    "base1": 0,
    "base2": 0,
    "base3": 0,
    "outCount": 2,
    "pitchCount": 1,
    "lastPitchSpeed": "146",
    "lastPitchType": "투심"
  }
]